{"frames": {

"bullet.png":
{
	"frame": {"x":1014,"y":95,"w":7,"h":1},
	"rotated": false,
	"trimmed": false,
	"spriteSourceSize": {"x":0,"y":0,"w":7,"h":1},
	"sourceSize": {"w":7,"h":1}
},
"fire.png":
{
	"frame": {"x":2,"y":2,"w":810,"h":340},
	"rotated": false,
	"trimmed": false,
	"spriteSourceSize": {"x":0,"y":0,"w":810,"h":340},
	"sourceSize": {"w":810,"h":340}
},
"ground-grad.png":
{
	"frame": {"x":814,"y":2,"w":168,"h":177},
	"rotated": false,
	"trimmed": true,
	"spriteSourceSize": {"x":0,"y":4,"w":168,"h":177},
	"sourceSize": {"w":168,"h":181}
},
"ground/g1.png":
{
	"frame": {"x":311,"y":344,"w":256,"h":100},
	"rotated": false,
	"trimmed": false,
	"spriteSourceSize": {"x":0,"y":0,"w":256,"h":100},
	"sourceSize": {"w":256,"h":100}
},
"ground/g2.png":
{
	"frame": {"x":2,"y":379,"w":256,"h":100},
	"rotated": false,
	"trimmed": false,
	"spriteSourceSize": {"x":0,"y":0,"w":256,"h":100},
	"sourceSize": {"w":256,"h":100}
},
"ground/g3.png":
{
	"frame": {"x":569,"y":366,"w":256,"h":100},
	"rotated": false,
	"trimmed": false,
	"spriteSourceSize": {"x":0,"y":0,"w":256,"h":100},
	"sourceSize": {"w":256,"h":100}
},
"ground/g4.png":
{
	"frame": {"x":260,"y":446,"w":256,"h":100},
	"rotated": false,
	"trimmed": false,
	"spriteSourceSize": {"x":0,"y":0,"w":256,"h":100},
	"sourceSize": {"w":256,"h":100}
},
"ground/g5.png":
{
	"frame": {"x":2,"y":481,"w":256,"h":96},
	"rotated": false,
	"trimmed": true,
	"spriteSourceSize": {"x":0,"y":4,"w":256,"h":96},
	"sourceSize": {"w":256,"h":100}
},
"ground/g6.png":
{
	"frame": {"x":518,"y":468,"w":256,"h":93},
	"rotated": false,
	"trimmed": true,
	"spriteSourceSize": {"x":0,"y":7,"w":256,"h":93},
	"sourceSize": {"w":256,"h":100}
},
"gui/life-dot-off.png":
{
	"frame": {"x":926,"y":274,"w":11,"h":11},
	"rotated": false,
	"trimmed": true,
	"spriteSourceSize": {"x":2,"y":2,"w":11,"h":11},
	"sourceSize": {"w":15,"h":15}
},
"gui/life-dot-on.png":
{
	"frame": {"x":926,"y":287,"w":11,"h":11},
	"rotated": false,
	"trimmed": true,
	"spriteSourceSize": {"x":2,"y":2,"w":11,"h":11},
	"sourceSize": {"w":15,"h":15}
},
"gui/logo-307.png":
{
	"frame": {"x":2,"y":344,"w":307,"h":33},
	"rotated": false,
	"trimmed": false,
	"spriteSourceSize": {"x":0,"y":0,"w":307,"h":33},
	"sourceSize": {"w":307,"h":33}
},
"gui/player-offscreen-left.png":
{
	"frame": {"x":946,"y":181,"w":24,"h":23},
	"rotated": false,
	"trimmed": false,
	"spriteSourceSize": {"x":0,"y":0,"w":24,"h":23},
	"sourceSize": {"w":24,"h":23}
},
"gui/player-offscreen-right.png":
{
	"frame": {"x":946,"y":206,"w":24,"h":23},
	"rotated": false,
	"trimmed": false,
	"spriteSourceSize": {"x":0,"y":0,"w":24,"h":23},
	"sourceSize": {"w":24,"h":23}
},
"gui/player-offscreen-up.png":
{
	"frame": {"x":940,"y":231,"w":23,"h":24},
	"rotated": false,
	"trimmed": false,
	"spriteSourceSize": {"x":0,"y":0,"w":23,"h":24},
	"sourceSize": {"w":23,"h":24}
},
"plane1/p1.png":
{
	"frame": {"x":880,"y":181,"w":64,"h":44},
	"rotated": false,
	"trimmed": true,
	"spriteSourceSize": {"x":0,"y":11,"w":64,"h":44},
	"sourceSize": {"w":64,"h":64}
},
"plane1/p10.png":
{
	"frame": {"x":926,"y":304,"w":15,"h":44},
	"rotated": false,
	"trimmed": true,
	"spriteSourceSize": {"x":25,"y":11,"w":15,"h":44},
	"sourceSize": {"w":64,"h":64}
},
"plane1/p2.png":
{
	"frame": {"x":814,"y":228,"w":58,"h":44},
	"rotated": false,
	"trimmed": true,
	"spriteSourceSize": {"x":3,"y":11,"w":58,"h":44},
	"sourceSize": {"w":64,"h":64}
},
"plane1/p3.png":
{
	"frame": {"x":962,"y":282,"w":52,"h":44},
	"rotated": false,
	"trimmed": true,
	"spriteSourceSize": {"x":6,"y":11,"w":52,"h":44},
	"sourceSize": {"w":64,"h":64}
},
"plane1/p4.png":
{
	"frame": {"x":814,"y":274,"w":46,"h":44},
	"rotated": false,
	"trimmed": true,
	"spriteSourceSize": {"x":9,"y":11,"w":46,"h":44},
	"sourceSize": {"w":64,"h":64}
},
"plane1/p5.png":
{
	"frame": {"x":814,"y":320,"w":40,"h":44},
	"rotated": false,
	"trimmed": true,
	"spriteSourceSize": {"x":12,"y":11,"w":40,"h":44},
	"sourceSize": {"w":64,"h":64}
},
"plane1/p6.png":
{
	"frame": {"x":984,"y":49,"w":34,"h":44},
	"rotated": false,
	"trimmed": true,
	"spriteSourceSize": {"x":15,"y":11,"w":34,"h":44},
	"sourceSize": {"w":64,"h":64}
},
"plane1/p7.png":
{
	"frame": {"x":984,"y":142,"w":28,"h":44},
	"rotated": false,
	"trimmed": true,
	"spriteSourceSize": {"x":18,"y":11,"w":28,"h":44},
	"sourceSize": {"w":64,"h":64}
},
"plane1/p8.png":
{
	"frame": {"x":904,"y":274,"w":20,"h":44},
	"rotated": false,
	"trimmed": true,
	"spriteSourceSize": {"x":22,"y":11,"w":20,"h":44},
	"sourceSize": {"w":64,"h":64}
},
"plane1/p9.png":
{
	"frame": {"x":920,"y":350,"w":14,"h":44},
	"rotated": false,
	"trimmed": true,
	"spriteSourceSize": {"x":25,"y":11,"w":14,"h":44},
	"sourceSize": {"w":64,"h":64}
},
"plane2/p1.png":
{
	"frame": {"x":814,"y":181,"w":64,"h":45},
	"rotated": false,
	"trimmed": true,
	"spriteSourceSize": {"x":0,"y":12,"w":64,"h":45},
	"sourceSize": {"w":64,"h":64}
},
"plane2/p10.png":
{
	"frame": {"x":943,"y":304,"w":14,"h":45},
	"rotated": false,
	"trimmed": true,
	"spriteSourceSize": {"x":26,"y":12,"w":14,"h":45},
	"sourceSize": {"w":64,"h":64}
},
"plane2/p2.png":
{
	"frame": {"x":880,"y":227,"w":58,"h":45},
	"rotated": false,
	"trimmed": true,
	"spriteSourceSize": {"x":3,"y":12,"w":58,"h":45},
	"sourceSize": {"w":64,"h":64}
},
"plane2/p3.png":
{
	"frame": {"x":965,"y":235,"w":52,"h":45},
	"rotated": false,
	"trimmed": true,
	"spriteSourceSize": {"x":6,"y":12,"w":52,"h":45},
	"sourceSize": {"w":64,"h":64}
},
"plane2/p4.png":
{
	"frame": {"x":972,"y":188,"w":46,"h":45},
	"rotated": false,
	"trimmed": true,
	"spriteSourceSize": {"x":9,"y":12,"w":46,"h":45},
	"sourceSize": {"w":64,"h":64}
},
"plane2/p5.png":
{
	"frame": {"x":862,"y":274,"w":40,"h":45},
	"rotated": false,
	"trimmed": true,
	"spriteSourceSize": {"x":12,"y":12,"w":40,"h":45},
	"sourceSize": {"w":64,"h":64}
},
"plane2/p6.png":
{
	"frame": {"x":984,"y":2,"w":34,"h":45},
	"rotated": false,
	"trimmed": true,
	"spriteSourceSize": {"x":15,"y":12,"w":34,"h":45},
	"sourceSize": {"w":64,"h":64}
},
"plane2/p7.png":
{
	"frame": {"x":984,"y":95,"w":28,"h":45},
	"rotated": false,
	"trimmed": true,
	"spriteSourceSize": {"x":18,"y":12,"w":28,"h":45},
	"sourceSize": {"w":64,"h":64}
},
"plane2/p8.png":
{
	"frame": {"x":940,"y":257,"w":20,"h":45},
	"rotated": false,
	"trimmed": true,
	"spriteSourceSize": {"x":22,"y":12,"w":20,"h":45},
	"sourceSize": {"w":64,"h":64}
},
"plane2/p9.png":
{
	"frame": {"x":904,"y":320,"w":14,"h":45},
	"rotated": false,
	"trimmed": true,
	"spriteSourceSize": {"x":25,"y":12,"w":14,"h":45},
	"sourceSize": {"w":64,"h":64}
}},
"meta": {
	"app": "http://www.codeandweb.com/texturepacker",
	"version": "1.0",
	"image": "game.png",
	"format": "RGBA8888",
	"size": {"w":1024,"h":1024},
	"scale": "1",
	"smartupdate": "$TexturePacker:SmartUpdate:7d6cac2ad0c5c347961448d934f263c2:698e267d1902607a4cc428239a7c47f5:fc2835210f98bae8e8c1b7f0a84c9321$"
}
}
